MANIFEST.in
Makefile
requirements.txt
setup.py
qqsuperman/__init__.py
qqsuperman/qqsuperman.py
qqsuperman.egg-info/PKG-INFO
qqsuperman.egg-info/SOURCES.txt
qqsuperman.egg-info/dependency_links.txt
qqsuperman.egg-info/not-zip-safe
qqsuperman.egg-info/requires.txt
qqsuperman.egg-info/top_level.txt
tests/.DS_Store
tests/__init__.py
tests/conftest.py
tests/test_qqsuperman.py
tests/sample/1.jpg
tests/sample/2.jpg