Metadata-Version: 1.0
Name: qqsuperman
Version: 0.1.0
Summary: The short of descriptions
Home-page: https://github.com/zeuxisoo/python-qqsuperman/
Author: Zeuxis Lo
Author-email: seekstudio@gmail.com
License: BSD
Platform: any
